MANIFEST.in
README.md
ez_setup.py
setup.py
idiscover/__init__.py
idiscover/arp.py
idiscover/discover.py
idiscover/oui.py
idiscover.egg-info/PKG-INFO
idiscover.egg-info/SOURCES.txt
idiscover.egg-info/dependency_links.txt
idiscover.egg-info/entry_points.txt
idiscover.egg-info/requires.txt
idiscover.egg-info/top_level.txt
idiscover.egg-info/zip-safe
idiscover/data/oui.txt