Metadata-Version: 1.1
Name: idiscover
Version: 1.1
Summary: Discover the devices (IP address & Manufacturer information) in a (sub)network
Home-page: https://github.com/semk/iDiscover
Author: Sreejith Kesavan
Author-email: sreejithemk@gmail.com
License: MIT License
Download-URL: https://github.com/semk/iDiscover/tarball/master
Keywords: Discover IP Address Manufacturer OUI ARP MAC
Platform: any
Classifier: Operating System :: POSIX
Classifier: Operating System :: Microsoft :: Windows
Classifier: Programming Language :: Python
Classifier: Environment :: Console
Classifier: Topic :: System :: Networking
Classifier: Topic :: Utilities
